README.rst
setup.py
peppertext/__init__.py
peppertext/base.py
peppertext/tests.py
peppertext.egg-info/PKG-INFO
peppertext.egg-info/SOURCES.txt
peppertext.egg-info/dependency_links.txt
peppertext.egg-info/not-zip-safe
peppertext.egg-info/requires.txt
peppertext.egg-info/top_level.txt